{
    "about": "à propos de nous",
    "description": "Bonjour ! Je suis Ade Faturahman, un développeur frontend passionné par la création d'applications web réactives et interactives en utilisant des technologies modernes telles que React et Tailwind CSS. Mon objectif est de fournir des interfaces utilisateur efficaces et épurées qui offrent une excellente expérience utilisateur.",
    "skills": "Compétences",
    "projects": "Projets",
    "contact": "Contact",
    "navbarTitle": "Mon Portfolio",
    "h1": "Bonjour, je suis Ade Faturahman",
    "p": "Développeur Frontend",
    "button": "Voir Mon Travail",
    "footer": "2024 Ade Faturahman. Tous droits réservés.",
    "h2": "Contactez-moi",
    "project1": "Application Web Réactive",
    "project2": "Plateforme E-Commerce",
    "project3": "Blog Personnel",
    "projectp1": "Une application web réactive construite avec React et Tailwind CSS.",
    "projectp2": "Une plateforme e-commerce avec des composants dynamiques et une authentification utilisateur.",
    "projectp3": "Un blog personnel créé avec React et Markdown pour la gestion du contenu.",
    "a": "En Savoir Plus",
    "submit": "Merci pour votre message !",
    "labelname": "Nom",
    "labelemail": "Email",
    "labelmassage": "Message",
    "sendmassage": "Envoyer un massage"
}
